flake8_formatting_junit.py
flake8_formatting_junit_xml.py
flake8_formatter_junit_xml/__init__.py
flake8_formatter_junit_xml/formatter.py
flake8_formatter_junit_xml-0.0.5.dist-info/DESCRIPTION.rst
flake8_formatter_junit_xml-0.0.5.dist-info/METADATA
flake8_formatter_junit_xml-0.0.5.dist-info/RECORD
flake8_formatter_junit_xml-0.0.5.dist-info/WHEEL
flake8_formatter_junit_xml-0.0.5.dist-info/entry_points.txt
flake8_formatter_junit_xml-0.0.5.dist-info/metadata.json
flake8_formatter_junit_xml-0.0.5.dist-info/top_level.txt
tests/__init__.py
tests/test_formatter.py
